AUTHORS
LICENSE
MANIFEST.in
README.rst
setup.py
appregister/__init__.py
appregister/base.py
django_appregister.egg-info/PKG-INFO
django_appregister.egg-info/SOURCES.txt
django_appregister.egg-info/dependency_links.txt
django_appregister.egg-info/not-zip-safe
django_appregister.egg-info/top_level.txt
requirements/install.txt
requirements/rtd.txt
requirements/test.txt
tests/test_appregister/__init__.py
tests/test_appregister/models.py
tests/test_appregister/questions.py
tests/test_appregister/questions2.py
tests/test_appregister/questions_error.py
tests/test_appregister/tests.py
tests/test_appregister/urls.py