Metadata-Version: 1.0
Name: django-appregister
Version: 0.3.1
Summary: A Django app that provides the building blocks for an app registry system
Home-page: http://appregsiter.readthedocs.org/
Author: Dougal Matthews
Author-email: dougal85@gmail.com
License: appregister
